panoptica_genai_protection/__init__.py
panoptica_genai_protection/auth.py
panoptica_genai_protection/auth_interface.py
panoptica_genai_protection/client.py
panoptica_genai_protection/settings.py
panoptica_genai_protection/gen/__init__.py
panoptica_genai_protection/gen/models.py
panoptica_genai_protection/gen/prompt_guardian_models.py
panoptica_genai_protection-0.1.18.dist-info/METADATA
panoptica_genai_protection-0.1.18.dist-info/WHEEL
panoptica_genai_protection-0.1.18.dist-info/top_level.txt
panoptica_genai_protection-0.1.18.dist-info/RECORD
