Metadata-Version: 2.1
Name: panoptica-genai-protection
Version: 0.1.18
Summary: Protecting GenAI from Prompt Injection
Author: marvin-team@cisco.com
Classifier: Programming Language :: Python :: 3
Classifier: Programming Language :: Python :: 3.9
Classifier: Programming Language :: Python :: 3.10
Classifier: Programming Language :: Python :: 3.11
Classifier: Programming Language :: Python :: 3.12
Classifier: Operating System :: OS Independent
Classifier: Intended Audience :: Developers
Classifier: Development Status :: 4 - Beta
Requires-Python: >=3.9
Requires-Dist: escherauth==0.3.4
Requires-Dist: pydantic>=2.5.1
Requires-Dist: httpx>=0.25.1
Requires-Dist: setuptools==70.2.0
